README.md
setup.cfg
setup.py
AIORedis_OpenTracing.egg-info/PKG-INFO
AIORedis_OpenTracing.egg-info/SOURCES.txt
AIORedis_OpenTracing.egg-info/dependency_links.txt
AIORedis_OpenTracing.egg-info/not-zip-safe
AIORedis_OpenTracing.egg-info/requires.txt
AIORedis_OpenTracing.egg-info/top_level.txt
aioredis_opentracing/__init__.py
aioredis_opentracing/instrument.py
aioredis_opentracing/tracing.py