Metadata-Version: 2.1
Name: AIORedis-OpenTracing
Version: 0.0.1
Summary: OpenTracing instrumentation for the asyncio Redis library
Home-page: https://github.com/Creativelair/AIORedis-Opentracing
Author: Daniel Jimenez
Author-email: danijimenez010@gmail.com
License: BSD
Download-URL: https://github.com/Creativelair/AIORedis-Opentracing/archive/v0.0.1.tar.gz
Platform: any
Classifier: Environment :: Web Environment
Classifier: Intended Audience :: Developers
Classifier: License :: OSI Approved :: BSD License
Classifier: Operating System :: OS Independent
Classifier: Programming Language :: Python
Classifier: Programming Language :: Python :: 2
Classifier: Programming Language :: Python :: 2.7
Classifier: Programming Language :: Python :: 3
Classifier: Programming Language :: Python :: 3.5
Classifier: Programming Language :: Python :: 3.6
Classifier: Programming Language :: Python :: 3.7
Classifier: Programming Language :: Python :: 3.8
Classifier: Programming Language :: Python :: Implementation :: CPython
Classifier: Programming Language :: Python :: Implementation :: PyPy
Classifier: Topic :: Internet :: WWW/HTTP :: Dynamic Content
Classifier: Topic :: Software Development :: Libraries :: Python Modules
Provides-Extra: tests
